README.md
setup.py
pyspeech/__init__.py
pyspeech/config.py
pyspeech.egg-info/PKG-INFO
pyspeech.egg-info/SOURCES.txt
pyspeech.egg-info/dependency_links.txt
pyspeech.egg-info/requires.txt
pyspeech.egg-info/top_level.txt