Metadata-Version: 1.0
Name: pyspeech
Version: 0.0.0
Summary: A python speech recognition framework
Home-page: UNKNOWN
Author: Xinjian Li
Author-email: lixinjian1217@gmail.com
License: UNKNOWN
Platform: UNKNOWN
